Metadata-Version: 2.1
Name: pollination-annual-daylight-enhanced.full
Version: 0.0.13
Summary: Annual daylight recipe for Pollination.
Home-page: https://github.com/pollination/annual-daylight-enhanced
Author: ladybug-tools
Author-email: info@ladybug.tools
Maintainer: mostapha, ladybug-tools
Maintainer-email: mostapha@ladybug.tools, info@ladybug.tools
License: PolyForm Shield License 1.0.0, https://polyformproject.org/wp-content/uploads/2020/06/PolyForm-Shield-1.0.0.txt
Project-URL: icon, https://raw.githubusercontent.com/ladybug-tools/artwork/master/icons_components/honeybee/png/annualrecipe.png
Project-URL: docker, https://hub.docker.com/r/ladybugtools/honeybee-radiance
Keywords: honeybee,radiance,ladybug-tools,daylight,annual-daylight
License-File: LICENSE
Requires-Dist: pollination-two-phase-daylight-coefficient>=1.1.52
Provides-Extra: viz
Requires-Dist: pollination-honeybee-display>=0.1.19; extra == "viz"
